nespy/__init__.py
nespy/batchmode.py
nespy/connection.py
nespy/datastream.py
nespy/exceptions.py
nespy/format.py
nespy/logicaloperators.py
nespy/operators.py
nespy/sinktypes.py
nespy/wrapper.py
nespy/grpc/CoordinatorRPCService_pb2.py
nespy/grpc/NodeStats_pb2.py
nespy/grpc/SerializableDataType_pb2.py
nespy/grpc/SerializableExpression_pb2.py
nespy/grpc/SerializableOperator_pb2.py
nespy/grpc/WorkerRPCService_pb2.py
nespy/grpc/__init__.py
nespy-0.0.6.dist-info/LICENSE
nespy-0.0.6.dist-info/METADATA
nespy-0.0.6.dist-info/WHEEL
nespy-0.0.6.dist-info/top_level.txt
nespy-0.0.6.dist-info/RECORD
