Metadata-Version: 2.1
Name: nespy
Version: 0.0.6
Summary: Python Client for NebulaStream
Home-page: https://www.nebula.stream/
License: Apache License 2.0
Project-URL: Source Code, https://github.com/nebulastream/nebulastream-python-client
Keywords: NebulaStream,NES,nespy,nebulastream-python-client,data science,IoT,data streams,data stream management
Platform: UNKNOWN
Classifier: Programming Language :: Python :: 3.6
Classifier: Programming Language :: Python :: 3.7
Classifier: Programming Language :: Python :: 3.8
Classifier: Programming Language :: Python :: 3.9
Classifier: Operating System :: POSIX :: Linux
Requires-Python: >=3.6
Requires-Dist: requests (>=2.25)
Requires-Dist: pyzmq (>=22)
Requires-Dist: pandas (>=1)
Requires-Dist: ipython (>=6)
Requires-Dist: google (>=3)
Requires-Dist: protobuf (>=3)
